frontmatter/__init__.py
frontmatter/conftest.py
frontmatter/default_handlers.py
frontmatter/util.py
python_frontmatter-1.0.1.dist-info/LICENSE
python_frontmatter-1.0.1.dist-info/METADATA
python_frontmatter-1.0.1.dist-info/WHEEL
python_frontmatter-1.0.1.dist-info/top_level.txt
python_frontmatter-1.0.1.dist-info/RECORD
