Metadata-Version: 2.1
Name: python-frontmatter
Version: 1.0.1
Summary: Parse and manage posts with YAML (or other) frontmatter
Home-page: https://github.com/eyeseast/python-frontmatter
Author: Chris Amico
Author-email: eyeseast@gmail.com
License: MIT
Keywords: frontmatter
Classifier: Development Status :: 5 - Production/Stable
Classifier: Intended Audience :: Developers
Classifier: License :: OSI Approved :: MIT License
Classifier: Natural Language :: English
Classifier: Programming Language :: Python :: 3
Classifier: Programming Language :: Python :: 3.8
Classifier: Programming Language :: Python :: 3.9
Classifier: Programming Language :: Python :: 3.10
Classifier: Programming Language :: Python :: 3.11
Classifier: Programming Language :: Python :: 3.12
Provides-Extra: test
Provides-Extra: docs
License-File: LICENSE
